trailscraper/__init__.py
trailscraper/boto_service_definitions.py
trailscraper/cli.py
trailscraper/cloudtrail.py
trailscraper/collection_utils.py
trailscraper/guess.py
trailscraper/iam.py
trailscraper/known-iam-actions.txt
trailscraper/policy_generator.py
trailscraper/s3_download.py
trailscraper/time_utils.py
trailscraper/record_sources/__init__.py
trailscraper/record_sources/cloudtrail_api_record_source.py
trailscraper/record_sources/local_directory_record_source.py
trailscraper-0.10.0.dist-info/METADATA
trailscraper-0.10.0.dist-info/WHEEL
trailscraper-0.10.0.dist-info/entry_points.txt
trailscraper-0.10.0.dist-info/licenses/LICENSE
trailscraper-0.10.0.dist-info/RECORD
