Metadata-Version: 2.4
Name: trailscraper
Version: 0.10.0
Summary: A command-line tool to get valuable information out of AWS CloudTrail
Project-URL: Homepage, http://github.com/flosell/trailscraper
Author-email: Florian Sellmayr <florian.sellmayr@gmail.com>
License: Apache License 2.0
License-File: LICENSE
Keywords: aws,cloud,cloudtrail,iam,trailscraper
Classifier: Development Status :: 3 - Alpha
Classifier: Intended Audience :: Developers
Classifier: Intended Audience :: System Administrators
Classifier: License :: OSI Approved :: Apache Software License
Classifier: Natural Language :: English
Classifier: Programming Language :: Python :: 3
Classifier: Programming Language :: Python :: 3.9
Classifier: Programming Language :: Python :: 3.10
Classifier: Programming Language :: Python :: 3.11
Classifier: Programming Language :: Python :: 3.12
Classifier: Programming Language :: Python :: 3.13
Classifier: Topic :: Security
Classifier: Topic :: Software Development :: Code Generators
Classifier: Topic :: System :: Systems Administration
Classifier: Topic :: Utilities
Requires-Python: >=3.10
Requires-Dist: boto3==1.38.3
Requires-Dist: click==8.1.8
Requires-Dist: dateparser==1.2.1
Requires-Dist: pytz==2025.2
Requires-Dist: ruamel-yaml==0.18.10
Requires-Dist: toolz==1.0.0
Provides-Extra: dev
Requires-Dist: bumpversion==0.6.0; extra == 'dev'
Requires-Dist: freezegun==1.5.1; extra == 'dev'
Requires-Dist: moto==4.2.14; extra == 'dev'
Requires-Dist: pylint==3.3.6; extra == 'dev'
Requires-Dist: pytest==8.3.5; extra == 'dev'
